{
    "!": [
        "ļ"
    ],
    "$": [
        "ṩ",
        "≴"
    ],
    "%": [
        "༔",
        "ზ"
    ],
    ")": [
        "☽"
    ],
    "*": [
        "٭",
        "⋆",
        "★",
        "☆",
        "✩",
        "✪",
        "✰",
        "✱",
        "✲",
        "✶",
        "✻",
        "❅"
    ],
    "+": [
        "Ⴕ",
        "ᆠ",
        "⁺",
        "₊",
        "∔",
        "⊹",
        "⌯",
        "⍅",
        "⍆",
        "⍏",
        "⍖",
        "⍭",
        "☩",
        "✚",
        "✢",
        "✤",
        "十"
    ],
    "-": [
        "‐",
        "‑",
        "⁃",
        "╴",
        "╶",
        "╸",
        "╺",
        "▭",
        "▰",
        "▱"
    ],
    "/": [
        "৴",
        "∕",
        "╱",
        "〳",
        "ノ"
    ],
    "0": [
        "ɸ",
        "ʘ",
        "Ф",
        "Օ",
        "ჶ",
        "⊙",
        "⌽",
        "Ⓘ",
        "ⓛ",
        "ⓣ",
        "☉"
    ],
    "1": [
        "ו",
        "ן",
        "Ί",
        "↿",
        "⒈",
        "ュ",
        "ユ"
    ],
    "2": [
        "ƻ",
        "ջ"
    ],
    "3": [
        "³",
        "Ǝ",
        "Ǯ",
        "ɜ",
        "ʒ",
        "З",
        "Э",
        "з",
        "э",
        "Ѯ",
        "ѯ",
        "Ҙ",
        "Ӡ",
        "ਤ",
        "ੜ",
        "੩",
        "૩",
        "౩",
        "ვ",
        "კ",
        "პ",
        "ჳ",
        "℈",
        "ℨ",
        "⒊",
        "ヨ",
        "彐"
    ],
    "4": [
        "վ",
        "⒋"
    ],
    "5": [
        "Ƽ",
        "ƽ",
        "ཏ",
        "ཧ",
        "⋝",
        "⒌",
        "ち",
        "ら"
    ],
    "6": [
        "б",
        "ნ",
        "⒍"
    ],
    "7": [
        "ァ",
        "ア",
        "フ"
    ],
    "8": [
        "ϐ",
        "Ϩ",
        "৪",
        "੪",
        "ଃ",
        "ᄝ",
        "ᇢ"
    ],
    "9": [
        "୨",
        "⒐"
    ],
    "<": [
        "≺",
        "☇",
        "〈",
        "〱",
        "く",
        "ぐ",
        "ㄑ"
    ],
    "=": [
        "≖"
    ],
    ">": [
        "≻",
        "〉"
    ],
    "?": [
        "‽"
    ],
    "A": [
        "Ǎ",
        "Ȃ",
        "ʌ",
        "Δ",
        "А",
        "Д",
        "д",
        "Ѧ",
        "ѧ",
        "Ӑ",
        "Ӓ",
        "ᇫ",
        "Ạ",
        "Ả",
        "Ậ",
        "Ἀ",
        "Ἁ",
        "Ᾰ",
        "Ᾱ",
        "Ὰ",
        "Ά",
        "Å",
        "ム",
        "ㄙ"
    ],
    "B": [
        "ɮ",
        "ʙ",
        "В",
        "в",
        "ѥ",
        "ც",
        "Ḃ",
        "Ḅ",
        "Ḇ"
    ],
    "C": [
        "Ƈ",
        "ƈ",
        "ʗ",
        "Ϛ",
        "С",
        "с",
        "Ҁ",
        "Ⴀ",
        "Ⴚ",
        "ℂ",
        "Ⅽ"
    ],
    "D": [
        "Ɖ",
        "Ɗ",
        "Ḋ",
        "Ḍ",
        "Ḏ",
        "Ḑ",
        "Ḓ"
    ],
    "E": [
        "ƹ",
        "Ȅ",
        "Ȇ",
        "Ё",
        "Е",
        "Ӗ",
        "Ḙ",
        "Ḛ",
        "Ḝ",
        "Ẹ",
        "Ẻ",
        "Ẽ",
        "Ễ",
        "Ệ",
        "Ἐ",
        "Ἑ",
        "Ἒ",
        "Ἓ",
        "Ἔ",
        "Ἕ",
        "Ἣ",
        "Ὲ",
        "Έ",
        "⁅",
        "乞"
    ],
    "F": [
        "Ƒ",
        "Ғ",
        "ᅣ",
        "Ḟ"
    ],
    "G": [
        "Ģ",
        "Ɠ",
        "Ǥ",
        "Ǵ",
        "ʛ",
        "Ḡ",
        "₢"
    ],
    "H": [
        ",༎",
        "Н",
        "н",
        "Ң",
        "ң",
        "Ҥ",
        "ҥ",
        "Ӈ",
        "ӈ",
        "Ⴌ",
        "ᅢ",
        "Ḣ",
        "Ḥ",
        "Ḧ",
        "ḧ",
        "Ḩ",
        "Ḫ",
        "Ἠ",
        "Ἡ",
        "Ἢ",
        "Ἤ",
        "Ἥ",
        "Ὴ",
        "Ή",
        "ℋ",
        "ㅐ",
        "㈠"
    ],
    "I": [
        "ɪ",
        "і",
        "آ",
        "Ị",
        "ị",
        "ⅰ",
        "⌶",
        "❙",
        "㆐",
        "工"
    ],
    "J": [
        "ɟ",
        "ϳ",
        "Ј",
        "ј",
        "ز",
        "ل",
        "ڵ",
        "ڶ",
        "ڷ",
        "╯",
        "╯丿",
        "㆜",
        "丁",
        "丿"
    ],
    "K": [
        "Ķ",
        "ķ",
        "Ƙ",
        "Ǩ",
        "Ќ",
        "К",
        "к",
        "Қ",
        "қ",
        "Ҝ",
        "ҝ",
        "Ҟ",
        "ҟ",
        "Ҡ",
        "ҡ",
        "Ӄ",
        "ӄ",
        "Ḱ",
        "Ḳ",
        "ḳ",
        "Ḵ",
        "ḵ",
        "K"
    ],
    "L": [
        "Ļ",
        "ɩ",
        "ʟ",
        "Լ",
        "ᄂ",
        "ᆫ",
        "Ḷ",
        "Ḻ",
        "Ⅼ",
        "⌊",
        "⌞",
        "┕",
        "┖",
        "┗",
        "ㄥ",
        "ㄴ",
        "乚"
    ],
    "M": [
        "ᄊ",
        "ᆻ",
        "Ḿ",
        "Ṁ",
        "Ṃ",
        "Ⅿ",
        "ㅆ",
        "从"
    ],
    "N": [
        "Ņ",
        "Ɲ",
        "ɴ",
        "א",
        "װ",
        "Ṅ",
        "Ṇ",
        "Ṉ",
        "Ṋ",
        "₦"
    ],
    "O": [
        "Ȏ",
        "О",
        "о",
        "Ѻ",
        "ѻ",
        "੦",
        "୦",
        "Ὀ",
        "Ὁ",
        "Ὸ",
        "Ό",
        "⃘",
        "◯",
        "❍",
        "〇",
        "ㅇ",
        "ㆁ"
    ],
    "P": [
        "Ƥ",
        "ƿ",
        "Р",
        "р",
        "բ",
        "ק",
        "Ῥ",
        "ℙ",
        "⍴",
        "户"
    ],
    "Q": [
        "ƍ",
        "Ǫ",
        "ǫ",
        "Ǭ",
        "ǭ",
        "Ձ",
        "ହ",
        "Ⴍ",
        "Ⴓ",
        "ღ",
        "Ọ",
        "Ộ",
        "Ợ",
        "ợℚ",
        "ℚ"
    ],
    "R": [
        "Ŗ",
        "ƦȐ",
        "Ȓ",
        "ʀ",
        "Ṙ",
        "Ṛ",
        "Ṝ",
        "ℝ",
        "℟"
    ],
    "S": [
        "Ϟ",
        "Ѕ",
        "ѕ",
        "Տ",
        "ऽ",
        "ડ",
        "ઽ",
        "ട",
        "Ⴝ",
        "Ṡ",
        "ṡ",
        "Ṩ",
        "⑀"
    ],
    "T": [
        "Ţ",
        "Ƭ",
        "Ʈ",
        "Т",
        "т",
        "Ҭ",
        "ҭ",
        "ᅮ",
        "Ṫ",
        "Ṭ",
        "Ṯ",
        "Ṱ",
        "⊤",
        "┭",
        "┮",
        "┯",
        "┰",
        "┱",
        "┲",
        "┳",
        "✝",
        "ㄒ",
        "ㅜ",
        "丅",
        "丆",
        "亇"
    ],
    "U": [
        "Ǉ",
        "ǔ",
        "Ǘ",
        "Ȗ",
        "ʊ",
        "Մ",
        "Ս",
        "ਪ",
        "ப",
        "Ⴎ",
        "Ṳ",
        "Ṵ",
        "ṵ",
        "Ṷ",
        "Ṻ",
        "Ụ",
        "ụ",
        "Ứ",
        "Ừ",
        "ừ",
        "Ử",
        "Ữ",
        "ㄩ"
    ],
    "V": [
        "Ѵ",
        "Ṽ",
        "ṽ",
        "Ṿ",
        "Ⅴ"
    ],
    "W": [
        "sẘ",
        "ש",
        "Ẇ",
        "ẇ",
        "Ẉ",
        "ẉ",
        "ẘ",
        "㈆",
        "㈧"
    ],
    "X": [
        "Ϫ",
        "ϰ",
        "Х",
        "х",
        "Ҳ",
        "ჯ",
        "Ẋ",
        "ẋ",
        "Ẍ",
        "Ⅹ",
        "ⅹ",
        "╳",
        "☓",
        "✕",
        "✖",
        "✗",
        "✘",
        "〤",
        "メ",
        "ㄨ",
        "乂"
    ],
    "Y": [
        "Ƴ",
        "ƴ",
        "Ү",
        "ץ",
        "Ẏ",
        "Ỵ",
        "Ỷ",
        "Ὑ",
        "Ῡ",
        "Ὺ",
        "Ύ",
        "ㄚ",
        "丫"
    ],
    "Z": [
        "Ƶ",
        "Հ",
        "Ẑ",
        "Ẓ",
        "ẓ",
        "Ẕ",
        "ẕ",
        "☡",
        "㆚",
        "之",
        "乙"
    ],
    "\\": [
        "∖",
        "╲",
        "、",
        "〵",
        "ヽ",
        "ㄟ",
        "丶",
        "乀"
    ],
    "_": [
        "▁"
    ],
    "a": [
        "Ƌ",
        "ƌ",
        "ǟ",
        "Ⴋ",
        "ẚ",
        "ạ",
        "ἀ",
        "ἁ",
        "ἆ",
        "ἇ",
        "ὰ",
        "ά",
        "ᾰ",
        "ᾱ",
        "ᾶ"
    ],
    "b": [
        "ƀ",
        "Ƅ",
        "ƅ",
        "ɓ",
        "Ϧ",
        "Ъ",
        "Ь",
        "Ե",
        "৳",
        "Ⴆ",
        "ს",
        "ხ",
        "ḃ",
        "ḅ",
        "ḇ",
        "␢",
        "♭"
    ],
    "c": [
        "ƈ",
        "ϲ"
    ],
    "d": [
        "ɗ",
        "ძ",
        "ḋ",
        "ḍ",
        "ḏ",
        "ḓ",
        "ⅾ"
    ],
    "e": [
        "е",
        "ℯ"
    ],
    "f": [
        "ƭ",
        "ʄ",
        "ḟ"
    ],
    "g": [
        "ɢ"
    ],
    "h": [
        "ɦ",
        "Һ",
        "һ",
        "Ⴙ",
        "ḣ",
        "ḥ",
        "ḩ"
    ],
    "i": [
        "أ",
        "ٲ",
        "ḭ",
        "ṫ",
        "Ỉ",
        "ỉ",
        "ἰ",
        "ἱ",
        "ὶ",
        "ί"
    ],
    "j": [
        "ڗ",
        "ڙ"
    ],
    "k": [
        "ƙ",
        "੍",
        "ḱ"
    ],
    "l": [
        "Ɩ",
        "ɭ",
        "ʅ",
        "།"
    ],
    "m": [
        "ɱ",
        "Պ",
        "௱",
        "ന",
        "ⅿ",
        "巾"
    ],
    "n": [
        "ƞ",
        "ɲ",
        "ɳ",
        "П",
        "ח",
        "ת"
    ],
    "o": [
        "☌",
        "♁"
    ],
    "p": [
        "ƥ",
        "Ṕ",
        "Ṗ",
        "ㄗ"
    ],
    "q": [
        "ƣ",
        "འ"
    ],
    "r": [
        "ɼ",
        "ɾ",
        "Г",
        "г",
        "ґ",
        "ٵ",
        "⌜",
        "┎",
        "┏",
        "╭",
        "「",
        "『"
    ],
    "s": [
        "ک"
    ],
    "t": [
        "ţ",
        "ƫ",
        "ʈ",
        "Է",
        "੮",
        "ṭ",
        "ṯ",
        "ṱ",
        "セ",
        "ヒ",
        "七"
    ],
    "u": [
        "ǖ",
        "ǘ",
        "ǚ",
        "ǜ",
        "Ц",
        "ц",
        "น",
        "Ự"
    ],
    "v": [
        "ѵ",
        "ⅴ",
        "⋁"
    ],
    "w": [
        "Ɯ",
        "ɯ",
        "Ѡ",
        "ѡ",
        "ѽ",
        "ա",
        "ധ",
        "ພ",
        "ຟ"
    ],
    "x": [
        "ҳ",
        "幺"
    ],
    "y": [
        "ʸ",
        "У",
        "у",
        "ẏ"
    ],
    "z": [
        "ƶ"
    ],
    "{": [],
    "|": [
        "ǀ",
        "І",
        "Ӏ",
        "׀",
        "ا",
        "ᅵ"
    ],
    "}": [],
    "~": [
        "ۤ",
        "≂",
        "≋"
    ],
    "¢": [
        "⍧"
    ],
    "¥": [
        "Ұ",
        "ұ"
    ],
    "§": [
        "≶"
    ],
    "©": [
        "Ⓒ",
        "Ⓖ",
        "Ⓤ",
        "ⓒ",
        "ⓖ",
        "ⓞ",
        "ⓢ",
        "◎",
        "㈇",
        "㉡",
        "㉢",
        "㉧",
        "㋒",
        "㋥",
        "㋶",
        "㋷"
    ],
    "«": [
        "≪",
        "ㄍ",
        "巜"
    ],
    "®": [
        "ѿ",
        "৩",
        "ଡ",
        "ଡ଼",
        "இ",
        "௫",
        "യ",
        "ൗ",
        "൫",
        "ῶ",
        "ῷ",
        "⃠",
        "℗",
        "⊘",
        "⊛",
        "⍟",
        "②",
        "③",
        "⑦",
        "⑫",
        "⑬",
        "⑰",
        "⑳",
        "Ⓐ",
        "Ⓓ",
        "Ⓔ",
        "Ⓕ",
        "Ⓗ",
        "Ⓙ",
        "Ⓚ",
        "Ⓛ",
        "Ⓝ",
        "Ⓟ",
        "Ⓡ",
        "Ⓣ",
        "Ⓥ",
        "Ⓧ",
        "Ⓨ",
        "Ⓩ",
        "ⓕ",
        "ⓚ",
        "ⓜ",
        "ⓝ",
        "ⓟ",
        "ⓡ",
        "ⓥ",
        "ⓧ",
        "ⓨ",
        "ⓩ",
        "➁",
        "➂",
        "㈌",
        "㉠",
        "㉦",
        "㉨",
        "㉩",
        "㉪",
        "㉬",
        "㉮",
        "㉰",
        "㉱",
        "㉷",
        "㉸",
        "㉹",
        "㉺",
        "㉿",
        "㊅",
        "㊇",
        "㊈",
        "㊉",
        "㊋",
        "㊌",
        "㊍",
        "㊏",
        "㊣",
        "㊤",
        "㊦",
        "㋐",
        "㋑",
        "㋓",
        "㋔",
        "㋕",
        "㋚",
        "㋛",
        "㋜",
        "㋝",
        "㋞",
        "㋡",
        "㋢",
        "㋣",
        "㋤",
        "㋦",
        "㋧",
        "㋨",
        "㋩",
        "㋪",
        "㋫",
        "㋭",
        "㋮",
        "㋯",
        "㋱",
        "㋲",
        "㋳",
        "㋹",
        "㋺",
        "㋽"
    ],
    "»": [
        "≫",
        "➻"
    ],
    "é": [
        "ǎ",
        "Ǒ",
        "ȁ",
        "ȃ",
        "ȅ",
        "ȇ",
        "ё",
        "ӑ",
        "ӓ",
        "ӗ",
        "Ӛ",
        "ӛ",
        "Ӟ",
        "ӟ",
        "Ӫ",
        "ӫ",
        "֓",
        "ؤ",
        "ڂ",
        "ڪ",
        "ۆ",
        "ۈ",
        "ۉ",
        "ۊ",
        "ے",
        "੬",
        "ઠ",
        "ଽ",
        "క",
        "໕",
        "༳",
        "ḉ",
        "ḕ",
        "Ḗ",
        "ḗ",
        "ḝ",
        "Ṍ",
        "Ṓ",
        "Ṥ",
        "ṥ",
        "Ṧ",
        "ṧ",
        "ả",
        "ẫ",
        "ậ",
        "ắ",
        "ằ",
        "ặ",
        "ẻ",
        "ẽ",
        "ể",
        "ễ",
        "ệ",
        "Ỏ",
        "ἐ",
        "ἑ",
        "ὀ",
        "ὁ",
        "ὲ",
        "έ",
        "ό",
        "≗",
        "≙",
        "≜",
        "≦",
        "≨",
        "⋚",
        "仺",
        "偆",
        "傄",
        "叁",
        "搉",
        "春",
        "歺",
        "甮"
    ],
    "—": [
        "ˍ",
        "˗",
        "ᅳ",
        "ᆖ",
        "ᆜ",
        "―",
        "∸",
        "≃",
        "≊",
        "≐",
        "≘",
        "≣",
        "⋍",
        "⌎",
        "⍘",
        "╾",
        "☰",
        "ニ",
        "ー",
        "ㄕ",
        "ㄧ",
        "ㅡ",
        "㆒",
        "㆓",
        "㆔",
        "一",
        "三",
        "二",
        "亖",
        "畺",
        "疅"
    ],
    "‘": [
        "ਚ",
        "ੲ",
        "༯",
        "ཙ",
        "ྩ"
    ],
    "“": [
        "ǁ",
        "‶",
        "∥",
        "❝"
    ],
    "”": [
        "‖",
        "Ⅱ",
        "ⅱ",
        "❞"
    ],
    "€": [],
    "ﬁ": [
        "ҕ",
        "ӣ",
        "մ",
        "ઉ",
        "ἠ",
        "ἡ",
        "ἢ",
        "ἣ",
        "ἤ",
        "ἥ",
        "ἦ",
        "ἧ",
        "ὴ",
        "ή",
        "ᾒ",
        "ᾓ",
        "ᾔ",
        "ᾕ",
        "ῆ",
        "ῇ",
        "⊞",
        "⌇",
        "⑃",
        "伉",
        "伒",
        "伔",
        "僃",
        "免",
        "凥",
        "坘",
        "垚",
        "奂",
        "崅",
        "忨",
        "梚",
        "氙",
        "氚",
        "氩",
        "畚",
        "痪"
    ],
    "ﬂ": [
        "Ո",
        "Ռ",
        "ո",
        "ռ",
        "י",
        "ಗ",
        "ก",
        "ཆ",
        "ཚ",
        "Ⴖ",
        "ჟ",
        "ᅦ",
        "ᅱ",
        "ᆋ",
        "ᆵ",
        "῁",
        "῍",
        "∄",
        "≾",
        "⊴",
        "⋂",
        "⍝",
        "〃",
        "が",
        "せ",
        "゙",
        "゛",
        "ガ",
        "コ",
        "ㄝ",
        "ㄿ",
        "ㅔ",
        "ㅟ",
        "ㆊ",
        "ㆌ",
        "仃",
        "仈",
        "仉",
        "仕",
        "仜",
        "伺",
        "佃",
        "但",
        "何",
        "佪",
        "冋",
        "凪",
        "凸",
        "刋",
        "利",
        "卩",
        "句",
        "叿",
        "员",
        "圢",
        "圱",
        "坈",
        "壨",
        "妅",
        "嵷",
        "嶤",
        "幻",
        "抲",
        "旦",
        "朾",
        "柯",
        "梱",
        "玒",
        "矼",
        "礉"
    ]
}